huaweicloudsdksmsapi/__init__.py
huaweicloudsdksmsapi/v1/__init__.py
huaweicloudsdksmsapi/v1/smsapi_async_client.py
huaweicloudsdksmsapi/v1/smsapi_client.py
huaweicloudsdksmsapi/v1/smsapi_credentials.py
huaweicloudsdksmsapi/v1/model/__init__.py
huaweicloudsdksmsapi/v1/model/batch_send_diff_sms_request.py
huaweicloudsdksmsapi/v1/model/batch_send_diff_sms_request_body.py
huaweicloudsdksmsapi/v1/model/batch_send_diff_sms_response.py
huaweicloudsdksmsapi/v1/model/batch_send_sms_request.py
huaweicloudsdksmsapi/v1/model/batch_send_sms_request_body.py
huaweicloudsdksmsapi/v1/model/batch_send_sms_response.py
huaweicloudsdksmsapi/v1/model/sms_content.py
huaweicloudsdksmsapi/v1/model/sms_id.py
huaweicloudsdksmsapi/v1/region/__init__.py
huaweicloudsdksmsapi/v1/region/smsapi_region.py
huaweicloudsdksmsapi-3.1.184.dist-info/METADATA
huaweicloudsdksmsapi-3.1.184.dist-info/WHEEL
huaweicloudsdksmsapi-3.1.184.dist-info/licenses/LICENSE
huaweicloudsdksmsapi-3.1.184.dist-info/RECORD
